moonito/__init__.py
moonito/visitor_traffic_filtering.py
moonito-1.0.0.dist-info/licenses/LICENSE
moonito-1.0.0.dist-info/METADATA
moonito-1.0.0.dist-info/WHEEL
moonito-1.0.0.dist-info/top_level.txt
moonito-1.0.0.dist-info/RECORD
