Metadata-Version: 2.4
Name: moonito
Version: 1.0.0
Summary: Visitor Traffic Filtering for Python web applications
Home-page: https://github.com/moonito-net/moonito-python
Author: Moonito
Author-email: Moonito <support@moonito.net>
Project-URL: Homepage, https://moonito.net
Project-URL: Documentation, https://moonito.net/docs
Project-URL: Repository, https://github.com/moonito-net/moonito-python
Project-URL: Bug Tracker, https://github.com/moonito-net/moonito-python/issues
Keywords: traffic filtering,visitor filtering,bot detection,security,web protection
Classifier: Development Status :: 5 - Production/Stable
Classifier: Intended Audience :: Developers
Classifier: Topic :: Internet :: WWW/HTTP
Classifier: Topic :: Security
Classifier: License :: OSI Approved :: MIT License
Classifier: Programming Language :: Python :: 3
Classifier: Programming Language :: Python :: 3.7
Classifier: Programming Language :: Python :: 3.8
Classifier: Programming Language :: Python :: 3.9
Classifier: Programming Language :: Python :: 3.10
Classifier: Programming Language :: Python :: 3.11
Classifier: Programming Language :: Python :: 3.12
Requires-Python: >=3.7
License-File: LICENSE
Dynamic: author
Dynamic: home-page
Dynamic: license-file
Dynamic: requires-python
